repo_sapiens/__init__.py
repo_sapiens/__main__.py
repo_sapiens/__version__.py
repo_sapiens/enums.py
repo_sapiens/exceptions.py
repo_sapiens/main.py
repo_sapiens/py.typed
repo_sapiens/webhook_server.py
repo_sapiens/agents/__init__.py
repo_sapiens/agents/backends.py
repo_sapiens/agents/react.py
repo_sapiens/agents/tools.py
repo_sapiens/cli/__init__.py
repo_sapiens/cli/credentials.py
repo_sapiens/cli/health.py
repo_sapiens/cli/init.py
repo_sapiens/cli/mcp.py
repo_sapiens/cli/migrate.py
repo_sapiens/cli/process_comment.py
repo_sapiens/cli/process_label.py
repo_sapiens/cli/update.py
repo_sapiens/config/__init__.py
repo_sapiens/config/credential_fields.py
repo_sapiens/config/mcp.py
repo_sapiens/config/repositories.yaml
repo_sapiens/config/settings.py
repo_sapiens/config/triggers.py
repo_sapiens/credentials/__init__.py
repo_sapiens/credentials/backend.py
repo_sapiens/credentials/encrypted_backend.py
repo_sapiens/credentials/environment_backend.py
repo_sapiens/credentials/exceptions.py
repo_sapiens/credentials/keyring_backend.py
repo_sapiens/credentials/resolver.py
repo_sapiens/engine/__init__.py
repo_sapiens/engine/branching.py
repo_sapiens/engine/checkpointing.py
repo_sapiens/engine/context.py
repo_sapiens/engine/event_classifier.py
repo_sapiens/engine/label_router.py
repo_sapiens/engine/multi_repo.py
repo_sapiens/engine/orchestrator.py
repo_sapiens/engine/parallel_executor.py
repo_sapiens/engine/recovery.py
repo_sapiens/engine/state_manager.py
repo_sapiens/engine/types.py
repo_sapiens/engine/stages/__init__.py
repo_sapiens/engine/stages/approval.py
repo_sapiens/engine/stages/base.py
repo_sapiens/engine/stages/code_review.py
repo_sapiens/engine/stages/comment_response.py
repo_sapiens/engine/stages/dependency_audit.py
repo_sapiens/engine/stages/docs_generation.py
repo_sapiens/engine/stages/execution.py
repo_sapiens/engine/stages/fix_execution.py
repo_sapiens/engine/stages/implementation.py
repo_sapiens/engine/stages/merge.py
repo_sapiens/engine/stages/plan_review.py
repo_sapiens-0.5.2.dist-info/licenses/LICENSE
repo_sapiens-0.5.2.dist-info/METADATA
repo_sapiens-0.5.2.dist-info/WHEEL
repo_sapiens-0.5.2.dist-info/entry_points.txt
repo_sapiens-0.5.2.dist-info/top_level.txt
repo_sapiens-0.5.2.dist-info/RECORD
