Metadata-Version: 2.4
Name: repo-sapiens
Version: 0.5.2
Summary: Intelligent repository automation and management tool
Author-email: savorywatt <maintainer@savorywatt.com>
License: MIT
Project-URL: Homepage, https://github.com/savorywatt/repo-sapiens
Project-URL: Documentation, https://github.com/savorywatt/repo-sapiens#readme
Project-URL: Repository, https://github.com/savorywatt/repo-sapiens
Project-URL: Bug Tracker, https://github.com/savorywatt/repo-sapiens/issues
Keywords: automation,repository,build,ci,management,gitea,ai,workflow
Classifier: Development Status :: 4 - Beta
Classifier: Intended Audience :: Developers
Classifier: Programming Language :: Python :: 3
Classifier: Programming Language :: Python :: 3.12
Classifier: Topic :: Software Development :: Build Tools
Classifier: Topic :: Software Development :: Quality Assurance
Requires-Python: >=3.12
License-File: LICENSE
Requires-Dist: pydantic>=2.5.0
Requires-Dist: pydantic-settings>=2.1.0
Requires-Dist: httpx>=0.25.0
Requires-Dist: structlog>=23.2.0
Requires-Dist: click>=8.1.0
Requires-Dist: pyyaml>=6.0
Requires-Dist: aiofiles>=23.2.0
Requires-Dist: keyring>=24.0.0
Requires-Dist: cryptography>=41.0.0
Requires-Dist: gitpython>=3.1.40
Requires-Dist: jinja2>=3.1.3
Requires-Dist: pygithub>=2.1.1
Requires-Dist: h2>=4.3.0
Provides-Extra: monitoring
Requires-Dist: prometheus-client>=0.19.0; extra == "monitoring"
Requires-Dist: fastapi>=0.109.0; extra == "monitoring"
Requires-Dist: uvicorn>=0.27.0; extra == "monitoring"
Provides-Extra: dev
Requires-Dist: pytest>=7.4.0; extra == "dev"
Requires-Dist: pytest-asyncio>=0.21.0; extra == "dev"
Requires-Dist: pytest-cov>=4.1.0; extra == "dev"
Requires-Dist: pytest-mock>=3.12.0; extra == "dev"
Requires-Dist: pytest-benchmark>=4.0.0; extra == "dev"
Requires-Dist: black>=23.12.0; extra == "dev"
Requires-Dist: ruff>=0.1.8; extra == "dev"
Requires-Dist: mypy>=1.7.0; extra == "dev"
Requires-Dist: pre-commit>=3.6.0; extra == "dev"
Requires-Dist: bandit[toml]>=1.7.6; extra == "dev"
Requires-Dist: types-PyYAML>=6.0; extra == "dev"
Requires-Dist: types-aiofiles>=23.2; extra == "dev"
Provides-Extra: all
Requires-Dist: repo-sapiens[monitoring]; extra == "all"
Provides-Extra: integration
Requires-Dist: python-on-whales>=0.70.0; extra == "integration"
Dynamic: license-file
